.gitignore
MANIFEST.in
README.rst
setup.cfg
setup.py
docs/HISTORY.txt
docs/LICENSE.GPL
docs/LICENSE.txt
docs/MANUAL.txt
raptus/__init__.py
raptus.multilanguagepfg.egg-info/PKG-INFO
raptus.multilanguagepfg.egg-info/SOURCES.txt
raptus.multilanguagepfg.egg-info/dependency_links.txt
raptus.multilanguagepfg.egg-info/entry_points.txt
raptus.multilanguagepfg.egg-info/namespace_packages.txt
raptus.multilanguagepfg.egg-info/not-zip-safe
raptus.multilanguagepfg.egg-info/requires.txt
raptus.multilanguagepfg.egg-info/top_level.txt
raptus/multilanguagepfg/__init__.py
raptus/multilanguagepfg/config.py
raptus/multilanguagepfg/configure.zcml
raptus/multilanguagepfg/patches.py
raptus/multilanguagepfg/setuphandlers.py
raptus/multilanguagepfg/skins.zcml
raptus/multilanguagepfg/Extensions/Install.py
raptus/multilanguagepfg/Extensions/__init__.py
raptus/multilanguagepfg/extender/__init__.py
raptus/multilanguagepfg/extender/fieldsBase.py
raptus/multilanguagepfg/extender/fieldset.py
raptus/multilanguagepfg/extender/form.py
raptus/multilanguagepfg/extender/formLikertField.py
raptus/multilanguagepfg/extender/formMailerAdapter.py
raptus/multilanguagepfg/extender/thanksPage.py
raptus/multilanguagepfg/profiles/default/metadata.xml
raptus/multilanguagepfg/profiles/default/raptus.multilanguagepfg_install.txt
raptus/multilanguagepfg/profiles/default/skins.xml
raptus/multilanguagepfg/profiles/uninstall/import_steps.xml
raptus/multilanguagepfg/profiles/uninstall/raptus.multilanguagepfg_uninstall.txt
raptus/multilanguagepfg/skins/raptus_multilanguagepfg/fg_base_view_p3.cpt
raptus/multilanguagepfg/skins/raptus_multilanguagepfg/fg_base_view_p3.cpt.metadata
raptus/multilanguagepfg/skins/raptus_multilanguagepfg/fg_edit_macros_p3.pt
raptus/multilanguagepfg/skins/raptus_multilanguagepfg/fg_thankspage_view_p3.pt