Metadata-Version: 1.0
Name: raptus.multilanguagepfg
Version: 1.0b4
Summary: Provides support for raptus.multilanguagefields in PloneFormGen
Home-page: https://github.com/Raptus/raptus.multilanguagepfg
Author: Raptus AG
Author-email: dev@raptus.com
License: GPL
Platform: UNKNOWN
Classifier: Programming Language :: Python
